singlecyclecpu/Defines.v
// Width
`define InstrWidth										32
`define AddrWidth											32
`define DataWidth											32
`define OpcodeWidth										7
`define Func3Width										3
`define Func7Width										7
`define RegNumWidth										5
`define ALUOpWidth										4
`define StateWidth										3
`define PCOpWidth											2

// PC
`define PCAdd4												0
`define PCAddImm											1
`define PCSetImm											2
`define PCClear												3

// States
`define IDLE													0
`define RegWrite											1
`define MemReadRegWrite								2
`define MemWrite											3
`define PCSelectWrite									4
`define	PCWrite												5
`define LuiRegWrite										6

// ALU operation
`define ADD														4'h0
`define SUB														4'h1
`define OR														4'h2
`define XOR														4'h3
`define AND														4'h4
`define LesserThanUnsigned						4'h5
`define LesserThanSigned							4'h6
`define ShiftRightUnsigned						4'h7
`define ShiftRightSigned							4'h8
`define ShiftLeftUnsigned							4'h9
`define ShiftLeftSigned								4'hA
`define GreaterThanOrEqualUnsigned		4'hB
`define GreaterThanOrEqualSigned			4'hC
`define Equal													4'hD
`define NotEqual											4'hE

singlecyclecpu/RegsFile.v
`include "Defines.v"
module RegsFile(
  input										clk,
	input										reset,
  input  [4:0]						regNum0,
  input  [4:0]						regNum1,
  output [`DataWidth-1:0] regReadData0, // DataWidth = 32
  output [`DataWidth-1:0] regReadData1,

  input										regsWriteEnable, // 1 => WRITE
  input  [4:0]						regWriteNum,
  input  [`DataWidth-1:0]	regWriteData
);

reg [`DataWidth-1:0] regs[31:0];

integer i;
initial for ( i = 0; i < 32; i=i+1) regs[i] = 0;
assign regReadData0 = (regNum0 != 0) ? regs[regNum0] : 0;
assign regReadData1 = (regNum1 != 0) ? regs[regNum1] : 0;

always @(*) if (reset) for ( i = 0; i < 32; i=i+1) regs[i] = 0;

// three ported register file
// read two ports combinationally
// write third port on falling edge of clock
// register 0 hardwired to 0

always @(negedge clk)
begin
  if (regsWriteEnable && regWriteNum != 0)
  begin
    regs[regWriteNum] <= regWriteData;
    // DO NOT CHANGE THIS display LINE!!!
    // 不要修改下面这行display语句！！！
    /**********************************************************************/
    $display("x%d = %h", regWriteNum, regWriteData);
    /**********************************************************************/
  end
end

endmodule

singlecyclecpu/DataMem.v
`include "Defines.v"
module DataMem(
	input											clk,
  input		[`AddrWidth-1:0]	memAddr, // AddrWidth = 32
  output reg	[`DataWidth-1:0]	memReadData, // DataWidth = 32
	input											memWriteEnable, // 1 => Write
  input		[`DataWidth-1:0]	memWriteData, 
	input		[`AddrWidth-1:0]	PC, // AddrWidth = 32
	input		[`Func3Width-1:0]	func3
);

reg  [`DataWidth-1:0] RAM[0:1023];

always @(*)
begin
	case (memAddr[1:0])
    0:
    case (func3)
      0: memReadData = { { 24{ RAM[memAddr[11:2]][7] } }, RAM[memAddr[11:2]][7:0] }; // lb
      1: memReadData = { { 16{ RAM[memAddr[11:2]][15] } }, RAM[memAddr[11:2]][15:0] }; // lh lhu
      2: memReadData = RAM[memAddr[11:2]]; // lw
      4: memReadData = { 24'b0 , RAM[memAddr[11:2]][7:0] }; // lbu
      5: memReadData = { 16'b0 , RAM[memAddr[11:2]][15:0] }; // lhu
    endcase
    1:
    case (func3)
      0: memReadData = { { 24{ RAM[memAddr[11:2]][15] } }, RAM[memAddr[11:2]][15:8] }; // lb lbu
      1: memReadData = { { 16{ RAM[memAddr[11:2]][23] } }, RAM[memAddr[11:2]][23:8] }; // lh lhu
      /* 2: memReadData = RAM[memAddr[11:2]]; // lw */
      4: memReadData = { 24'b0 , RAM[memAddr[11:2]][15:8] }; // lbu
      5: memReadData = { 16'b0 , RAM[memAddr[11:2]][23:8] }; // lhu
    endcase
    2:
    case (func3)
      0: memReadData = { { 24{ RAM[memAddr[11:2]][23] } }, RAM[memAddr[11:2]][23:16] }; // lb lbu
      1: memReadData = { { 16{ RAM[memAddr[11:2]][31] } }, RAM[memAddr[11:2]][31:16] }; // lh lhu
      /* 2: memReadData = RAM[memAddr[11:2]]; // lw */
      4: memReadData = { 24'b0 , RAM[memAddr[11:2]][23:16] }; // lbu
      5: memReadData = { 16'b0 , RAM[memAddr[11:2]][31:16] }; // lhu
    endcase
    3:
    case (func3)
      0: memReadData = { { 24{ RAM[memAddr[11:2]][31] } }, RAM[memAddr[11:2]][31:24] }; // lb lbu
      /* 1: memReadData = { { 16{ RAM[memAddr[11:2]][15] } }, RAM[memAddr[11:2]][15:0] }; // lh lhu */
      /* 2: memReadData = RAM[memAddr[11:2]]; // lw */
      4: memReadData = { 24'b0 , RAM[memAddr[11:2]][31:24] }; // lbu
      /* 5: memReadData = { 16'b0 , RAM[memAddr[11:2]][31:16] }; // lhu */
    endcase
  endcase
end

always @(negedge clk)
begin
	if (memWriteEnable)
  begin
    case (memAddr[1:0])
      0:
      case (func3)
        0: RAM[memAddr[11:2]][7:0] = memWriteData[7:0]; // sb
        1: RAM[memAddr[11:2]][15:0]= memWriteData[15:0]; // sh
        2: RAM[memAddr[11:2]] = memWriteData; // sw
      endcase
      1:
      case (func3)
        0: RAM[memAddr[11:2]][15:8] = memWriteData[7:0]; // sb
        1: RAM[memAddr[11:2]][23:8]= memWriteData[15:0]; // sh
        /* 2: RAM[memAddr[11:2]] = memWriteData; // sw */
      endcase
      2:
      case (func3)
        0: RAM[memAddr[11:2]][23:16] = memWriteData[7:0]; // sb
        1: RAM[memAddr[11:2]][31:16]= memWriteData[15:0]; // sh
        /* 2: RAM[memAddr[11:2]] = memWriteData; // sw */
      endcase
      3:
      case (func3)
        0: RAM[memAddr[11:2]][31:24] = memWriteData[7:0]; // sb
        /* 1: RAM[memAddr[11:2]][15:0]= memWriteData[15:0]; // sh */
        /* 2: RAM[memAddr[11:2]] = memWriteData; // sw */
      endcase
    endcase
  end
end
always @(posedge clk)
begin
	if(memWriteEnable)
	begin
		// DO NOT CHANGE THIS display LINE!!!
		// 不要修改下面这行display语句！！！
		// 对于所有的store指令，都输出位于写入目标地址四字节对齐处的32位数据，不需要修改下面的display语句
		/******************************************************************************************************/
		$display("pc = %h: dataaddr = %h, memdata = %h", PC, {memAddr[31:2],2'b00}, RAM[memAddr[11:2]]);
		/******************************************************************************************************/
	end
end
endmodule

singlecyclecpu/Controller.v
`include "Defines.v"
module Controller (
	input								clk,
	input								reset,
	input		[`StateWidth-1:0]		state, // StateWidth = 4
	
	input		[`Func3Width-1:0]		func3, // Func3Width = 3
	input		[`DataWidth-1:0]		imm, // DataWidth = 32
	input		[`DataWidth-1:0]		regReadData1,
	input		[`DataWidth-1:0]		aluO,
	input		[`DataWidth-1:0]		PC,

	output	reg					regWriteEnable,
	output	reg	[`DataWidth-1:0]	regWriteData,
	output	reg					pcWriteEnable,
	output	reg	[`DataWidth-1:0]				pcWriteData
);

reg   [`AddrWidth-1:0]    memAddr;
wire  [`DataWidth-1:0]    memReadData;
reg                       memWriteEnable;
reg   [`DataWidth-1:0]    memWriteData;
reg   [`AddrWidth-1:0]    Addr[1:0];

initial begin
	pcWriteData = 0;
	pcWriteEnable	= 0;
end

always @(*) 
begin
	if (reset)
  begin
    pcWriteEnable     = 1;
    pcWriteData       = 0;
  end
	else 
	case (state)
		`IDLE:
    begin
      regWriteData    = 0;
      regWriteEnable  = 0;
      memWriteEnable  = 0;
      memWriteData    = 0;
      pcWriteEnable   = 0;
    end
		`RegWrite:
		begin
			regWriteData    = aluO;
      regWriteEnable  = 1;
      memWriteEnable  = 0;
      memWriteData    = 0;
      pcWriteEnable   = 0;
		end	
		`MemReadRegWrite:
    begin
      memAddr         = aluO;
      regWriteData    = memReadData;
      regWriteEnable  = 1;
      memWriteEnable  = 0;
      memWriteData    = 0;
      pcWriteEnable   = 0;
    end
		`MemWrite:
		begin
			memAddr         = aluO;
      memWriteData    = regReadData1;
      memWriteEnable  = 1;
      regWriteData    = 0;
      regWriteEnable  = 0;
      pcWriteEnable   = 0;
		end
		`PCSelectWrite:
    begin
      if (aluO)
      begin
        pcWriteEnable   = 1;
        pcWriteData     = PC + imm;
			end
			else pcWriteEnable = 0;
      regWriteData    = 0;
      regWriteEnable  = 0;
      memWriteEnable  = 0;
      memWriteData    = 0;
    end
		`PCWrite:
    begin
      pcWriteEnable   = 1;
      pcWriteData     = aluO;
      regWriteData    = PC;
      regWriteEnable  = 1;
      memWriteEnable  = 0;
      memWriteData    = 0;
    end
    `LuiRegWrite:
    begin
      regWriteData    = imm;
      regWriteEnable  = 1;
      memWriteEnable  = 0;
      memWriteData    = 0;
      pcWriteEnable   = 0;
    end
	endcase
end
DataMem mem(clk, memAddr, memReadData, memWriteEnable, memWriteData, PC, func3);
endmodule

singlecyclecpu/ALU.v
`include "Defines.v"
module ALU (
  input       [`ALUOpWidth-1:0]	aluOp, // ALUOpWidth = 4
  input       [`DataWidth-1:0]  aluX, aluY, // DataWidth = 32
  output	reg	[`DataWidth-1:0]  aluO
);

always @(*)
case (aluOp)
	`ADD:													aluO = aluX +  aluY;
	`SUB:													aluO = aluX -  aluY;
	`OR:													aluO = aluX |  aluY;
	`XOR:													aluO = aluX ^  aluY;
	`AND:													aluO = aluX &  aluY;
	`LesserThanUnsigned:					aluO = aluX <  aluY;
	`LesserThanSigned:						aluO = $signed(aluX) < $signed(aluY);
	`ShiftRightUnsigned:					aluO = aluX >> (aluY[4:0]);
	`ShiftRightSigned:						aluO = $signed(aluX) >>> (aluY[4:0]);
	`ShiftLeftUnsigned:						aluO = aluX << (aluY[4:0]); 
	`ShiftLeftSigned:							aluO = aluX << (aluY[4:0]);
	`GreaterThanOrEqualUnsigned:	aluO = aluX >= aluY;
	`GreaterThanOrEqualSigned:		aluO = $signed(aluX) >= $signed(aluY);
	`Equal:												aluO = aluX == aluY;
	`NotEqual:										aluO = aluX != aluY;
endcase
endmodule

singlecyclecpu/Execute.v
`include "Defines.v"
module Execute (
	input														clk,
	input														reset,
	input				[`OpcodeWidth-1:0]	opcode, // OpcodeWidth = 7
	input				[`Func3Width-1:0]		func3, // Func3Width = 3
	input				[`Func7Width-1:0]		func7, // Func7Width = 7
	input				[`RegNumWidth-1:0]	regNum0, // RegNumWidth = 5
	input				[`RegNumWidth-1:0]	regNum1,
	input				[`RegNumWidth-1:0]	regWriteNum,
	input				[`DataWidth-1:0]		imm, // DataWidth = 32
	input				[`AddrWidth-1:0]		PC, // AddrWidth = 32
	output													pcWriteEnable,
	output			[`DataWidth-1:0]		pcWriteData
);

reg		[`ALUOpWidth-1:0]	aluOp; // ALUOpWidth = 5
reg		[`DataWidth-1:0]	aluX;
reg		[`DataWidth-1:0]	aluY;
wire	[`DataWidth-1:0]	aluO;
reg		[`StateWidth-1:0] state;
wire	[`DataWidth-1:0]	regReadData0;
wire	[`DataWidth-1:0]	regReadData1;
wire										regWriteEnable;
wire		[`DataWidth-1:0]	regWriteData;
reg		[`AddrWidth-1:0]	memAddr; // AddrWidth = 32
wire										memReadEnable;
wire	[`DataWidth-1:0]	memReadData;
wire										memWriteEnable;
reg		[`DataWidth-1:0]	memWriteData;

always @(*)
begin
	if (reset) begin
		aluOp						=	`ADD;
		aluX						=	0;
		aluY						=	0;
		state						=	`IDLE;
	end
	else if (clk)
	begin
	case (opcode)
		7'b0110011: // FMT R
		begin
			case (func3)
				0: aluOp		=	func7[5] ? `SUB : `ADD;	// add sub
				1: aluOp		=	`ShiftLeftUnsigned;	// sll
				2: aluOp		=	`LesserThanSigned;	// slt
				3: aluOp		=	`LesserThanUnsigned; // sltu
				4: aluOp		=	`XOR; // xor
				5: aluOp		=	func7[5] ?	`ShiftRightSigned : `ShiftRightUnsigned; // srl sra
				6: aluOp		=	`OR; // or
				7: aluOp		=	`AND; // and
			endcase

			aluX					=	regReadData0;
			aluY					=	regReadData1;

			state					=	`RegWrite;
		end
		7'b0010011: // FMT I
		begin
			case (func3)
				0: aluOp		=	`ADD;	// addi
				1: aluOp		=	`ShiftLeftUnsigned;	// slli
				2: aluOp		=	`LesserThanSigned;	// slti
				3: aluOp		=	`LesserThanUnsigned; // sltiu
				4: aluOp		=	`XOR; // xori
				5: aluOp		=	imm[10] ?	`ShiftRightSigned : `ShiftRightUnsigned; // srli srai
				6: aluOp		=	`OR; // ori
				7: aluOp		=	`AND; // andi
			endcase

			aluX					=	regReadData0;
			aluY					=	imm;

			state					=	`RegWrite;
		end
		7'b0000011: // FMT I lb lh lw lbu lhu
		begin
			aluX					=	regReadData0;
			aluY					=	imm;
			aluOp					=	`ADD;

			state					=	`MemReadRegWrite;
		end
		7'b0100011: // FMT S sb sh sw
		begin
			aluX					=	regReadData0;
			aluY					=	imm;
			aluOp					=	`ADD;
			
			state					=	`MemWrite;
		end
		7'b1100011: // FMT B
		begin
			case (func3)
				0: aluOp		=	`Equal; // beq
				1: aluOp		=	`NotEqual; // bne
				4: aluOp		=	`LesserThanSigned; // blt
				5: aluOp		=	`GreaterThanOrEqualSigned; // bge
				6: aluOp		=	`LesserThanUnsigned; // bltu
				7: aluOp		=	`GreaterThanOrEqualUnsigned; // bgeu
			endcase
			aluX					=	regReadData0;
			aluY					=	regReadData1;

			state					=	`PCSelectWrite;
		end
		7'b1101111: // FMT J jal
		begin
			aluX					=	PC;
			aluY					=	imm;
			aluOp					=	`ADD;

			state					=	`PCWrite;
		end
		7'b1100111: // FMT I jalr
		begin
			aluX					=	regReadData0;
			aluY					=	imm;
			aluOp					=	`ADD;
			
			state					=	`PCWrite;
		end
		7'b0110111: // FMT U lui
		begin
			state					=	`LuiRegWrite;
		end
		7'b0010111: // FMT U auipc
		begin
			aluX					=	PC;
			aluY					=	imm;
			aluOp					=	`ADD;

			state					=	`RegWrite;
		end
		default: state	= `IDLE;
	endcase
	end
end

ALU	alu(aluOp, aluX, aluY, aluO);

Controller control(
	clk, reset, state, 
	func3, imm, regReadData1, aluO, PC,
	regWriteEnable, regWriteData, pcWriteEnable, pcWriteData
);

RegsFile RF(
	clk, reset, regNum0, regNum1, regReadData0, regReadData1, 
	regWriteEnable, regWriteNum, regWriteData
);
endmodule

singlecyclecpu/Decode.v
`include "Defines.v"
module Decode (
	input											clk,
	input											reset,
	input		[`InstrWidth-1:0]	instr, // InstrWidth = 32
	input		[`AddrWidth-1:0]	pcReadData, // AddrWidth = 32
	output								pcWriteEnable,
	output	[`DataWidth-1:0]	pcWriteData // DataWidth = 32
);

wire	[`OpcodeWidth-1:0]	opcode			= instr[6:0]; // OpcodeWidth = 7
wire	[`Func3Width-1:0]		func3				= instr[14:12]; // Func3Width = 3
wire	[`Func7Width-1:0]		func7				= instr[31:25]; // Func7Width = 7
wire	[`RegNumWidth-1:0]	regWriteNum	= instr[11:7]; // RegNumWidth = 5
wire	[`RegNumWidth-1:0]	regNum0			= instr[19:15];
wire	[`RegNumWidth-1:0]	regNum1			= instr[24:20];
reg		[`DataWidth-1:0]	imm;
initial imm = 0;

always @(*)
begin
	case(opcode)
		7'b0010011, 7'b1100111, 7'b0000011:	// FMT I
			case(func3)
				3'b001, 3'b101: 
					imm = { 20'b0, instr[31:20] };
				default:
					imm = { { 20{ instr[31] } }, instr[31:20] };
			endcase
		7'b0100011:	// FMT S
			imm	= { { 20{ instr[31] } }, instr[31:25], instr[11:7] };
		7'b1100011: // FMT B
			imm = { { 20{ instr[31] } }, instr[7], instr[30:25], instr[11:8], 1'b0 };
		7'b0010111, 7'b0110111: // FMT U
			imm = { instr[31:12], 12'b0 };
		7'b1101111: // FMT J
			imm = { { 13{ instr[31] } }, instr[19:12], instr[20], instr[30:21], 1'b0 };
		default:
			imm = 32'bz;
	endcase
end

Execute EX(
	clk, reset, opcode, func3, func7, 
	regNum0, regNum1, regWriteNum, imm,
	pcReadData, pcWriteEnable, pcWriteData
);
endmodule

singlecyclecpu/InstrMem_1.v
`include "Defines.v"
module InstrMem(
  input  [`AddrWidth-1:0]	instrAddr, // AddrWidth = 32
  output [`InstrWidth-1:0]	instrData // InstrWidth = 32
);

reg [`InstrWidth-1:0] RAM[0:1023];

assign instrData = RAM[instrAddr[11:2]]; 
endmodule

singlecyclecpu/CPU.v
`include "Defines.v"
module CPU (
	input											clk,
	input											reset,
	output	[`AddrWidth-1:0]	PC // AddrWidth = 32
);

reg		[`AddrWidth-1:0] pcData[1:0]; // get pcData
wire	[`InstrWidth-1:0]	instr; // InstrWidth = 32
wire	[`AddrWidth-1:0]	pcWriteData;
wire	pcWriteEnable;
initial pcData[0] = -4;
assign PC = pcData[0];

always @(*) if (reset) pcData[0] = 0;

always @(*)
begin
	pcData[1] = pcData[0] + 4;
end

always @(posedge clk)
begin
	pcData[0] <= pcWriteEnable ? pcWriteData : pcData[1];
end

InstrMem	instrMem(.instrAddr(pcData[0]), .instrData(instr));

Decode ID(clk, reset, instr, pcData[0], pcWriteEnable, pcWriteData);
endmodule

singlecyclecpu/tb/CPU_tb.v
`timescale 1ns/1ns

module CPU_tb();
reg					clk;
reg					reset;
wire[31:0]	pc;
    
CPU cpu(clk, reset, pc);

integer counter = 0;

initial begin
	$dumpfile("build/test.vcd");
	$dumpvars;
  $readmemh("tb/riscv32_sim8.dat", cpu.instrMem.RAM);
  /* $readmemh("tb/riscv32_sim2.dat", cpu.ID.mem.RAM); */
  clk = 1;
	reset = 0;
end

always begin
   #300 clk = ~clk;
  
   if (clk == 1'b1) 
   begin
      counter = counter + 1;
      //comment out all display line(s) for online judge
      if (pc > 32'h00000500) // set to the address of the last instruction
       begin

         $stop;
       end
   end  
end //end always

endmodule

singlecyclecpu/build/test.vcd
$date
	Mon May  6 01:48:46 2024
$end
$version
	Icarus Verilog
$end
$timescale
	1ns
$end
$scope module CPU_tb $end
$var wire 32 ! pc [31:0] $end
$var reg 1 " clk $end
$var reg 1 # reset $end
$var integer 32 $ counter [31:0] $end
$scope module cpu $end
$var wire 32 % PC [31:0] $end
$var wire 1 " clk $end
$var wire 1 # reset $end
$var wire 1 & pcWriteEnable $end
$var wire 32 ' pcWriteData [31:0] $end
$var wire 32 ( instr [31:0] $end
$scope module ID $end
$var wire 1 " clk $end
$var wire 32 ) pcReadData [31:0] $end
$var wire 1 # reset $end
$var wire 5 * regWriteNum [4:0] $end
$var wire 5 + regNum1 [4:0] $end
$var wire 5 , regNum0 [4:0] $end
$var wire 1 & pcWriteEnable $end
$var wire 32 - pcWriteData [31:0] $end
$var wire 7 . opcode [6:0] $end
$var wire 32 / instr [31:0] $end
$var wire 7 0 func7 [6:0] $end
$var wire 3 1 func3 [2:0] $end
$var reg 32 2 imm [31:0] $end
$scope module EX $end
$var wire 32 3 PC [31:0] $end
$var wire 1 " clk $end
$var wire 3 4 func3 [2:0] $end
$var wire 7 5 func7 [6:0] $end
$var wire 32 6 imm [31:0] $end
$var wire 7 7 opcode [6:0] $end
$var wire 5 8 regNum0 [4:0] $end
$var wire 5 9 regNum1 [4:0] $end
$var wire 5 : regWriteNum [4:0] $end
$var wire 1 # reset $end
$var wire 1 ; regWriteEnable $end
$var wire 32 < regWriteData [31:0] $end
$var wire 32 = regReadData1 [31:0] $end
$var wire 32 > regReadData0 [31:0] $end
$var wire 1 & pcWriteEnable $end
$var wire 32 ? pcWriteData [31:0] $end
$var wire 32 @ aluO [31:0] $end
$var reg 4 A aluOp [3:0] $end
$var reg 32 B aluX [31:0] $end
$var reg 32 C aluY [31:0] $end
$var reg 3 D state [2:0] $end
$scope module RF $end
$var wire 1 " clk $end
$var wire 5 E regNum0 [4:0] $end
$var wire 5 F regNum1 [4:0] $end
$var wire 5 G regWriteNum [4:0] $end
$var wire 1 # reset $end
$var wire 1 ; regsWriteEnable $end
$var wire 32 H regWriteData [31:0] $end
$var wire 32 I regReadData1 [31:0] $end
$var wire 32 J regReadData0 [31:0] $end
$var integer 32 K i [31:0] $end
$upscope $end
$scope module alu $end
$var wire 4 L aluOp [3:0] $end
$var wire 32 M aluX [31:0] $end
$var wire 32 N aluY [31:0] $end
$var reg 32 O aluO [31:0] $end
$upscope $end
$scope module control $end
$var wire 32 P PC [31:0] $end
$var wire 32 Q aluO [31:0] $end
$var wire 1 " clk $end
$var wire 3 R func3 [2:0] $end
$var wire 32 S imm [31:0] $end
$var wire 32 T regReadData1 [31:0] $end
$var wire 1 # reset $end
$var wire 3 U state [2:0] $end
$var wire 32 V memReadData [31:0] $end
$var reg 32 W memAddr [31:0] $end
$var reg 32 X memWriteData [31:0] $end
$var reg 1 Y memWriteEnable $end
$var reg 32 Z pcWriteData [31:0] $end
$var reg 1 & pcWriteEnable $end
$var reg 32 [ regWriteData [31:0] $end
$var reg 1 ; regWriteEnable $end
$scope module mem $end
$var wire 32 \ PC [31:0] $end
$var wire 1 " clk $end
$var wire 3 ] func3 [2:0] $end
$var wire 32 ^ memAddr [31:0] $end
$var wire 32 _ memWriteData [31:0] $end
$var wire 1 Y memWriteEnable $end
$var reg 32 ` memReadData [31:0] $end
$upscope $end
$upscope $end
$upscope $end
$upscope $end
$scope module instrMem $end
$var wire 32 a instrAddr [31:0] $end
$var wire 32 b instrData [31:0] $end
$upscope $end
$upscope $end
$upscope $end
$enddefinitions $end
$comment Show the parameter values. $end
$dumpall
$end
#0
$dumpvars
b100000000001010010011 b
b0 a
bx `
b0 _
bx ^
b0 ]
b0 \
b1 [
b0 Z
0Y
b0 X
bx W
bx V
b1 U
b0 T
b1 S
b0 R
b1 Q
b0 P
b1 O
b1 N
b0 M
b0 L
b100000 K
b0 J
b0 I
b1 H
b101 G
b1 F
b0 E
b1 D
b1 C
b0 B
b0 A
b1 @
b0 ?
b0 >
b0 =
b1 <
1;
b101 :
b1 9
b0 8
b10011 7
b1 6
b0 5
b0 4
b0 3
b1 2
b0 1
b0 0
b100000000001010010011 /
b10011 .
b0 -
b0 ,
b1 +
b101 *
b0 )
b100000000001010010011 (
b0 '
0&
b0 %
b0 $
0#
1"
b0 !
$end
#300
0"
#600
b10 <
b10 H
b10 [
b10 @
b10 O
b10 Q
b10 C
b10 N
b10 +
b10 9
b10 F
b110 *
b110 :
b110 G
b10 2
b10 6
b10 S
b1000000000001100010011 (
b1000000000001100010011 /
b1000000000001100010011 b
b100 !
b100 %
b100 )
b100 3
b100 P
b100 \
b100 a
b1 $
1"
#900
0"
#1200
b11 <
b11 H
b11 [
b1 B
b1 M
b11 @
b11 O
b11 Q
b10 =
b10 I
b10 T
b1 >
b1 J
b10 C
b10 N
b110 +
b110 9
b110 F
b101 ,
b101 8
b101 E
b111 *
b111 :
b111 G
b110011 .
b110011 7
bz 2
bz 6
bz S
b11000101000001110110011 (
b11000101000001110110011 /
b11000101000001110110011 b
b1000 !
b1000 %
b1000 )
b1000 3
b1000 P
b1000 \
b1000 a
b10 $
1"
#1500
0"
#1800
b101 <
b101 H
b101 [
b101 @
b101 O
b101 Q
b11 B
b11 M
b11 >
b11 J
b111 ,
b111 8
b111 E
b1000 *
b1000 :
b1000 G
b11000111000010000110011 (
b11000111000010000110011 /
b11000111000010000110011 b
b1100 !
b1100 %
b1100 )
b1100 3
b1100 P
b1100 \
b1100 a
b11 $
1"
#2100
0"
#2400
b0 B
b0 M
b0 @
b0 O
b0 Q
0;
b0 <
b0 H
b0 [
1Y
b101 X
b101 _
b0 W
b0 ^
b101 =
b101 I
b101 T
b0 >
b0 J
b11 D
b11 U
b0 C
b0 N
b0 2
b0 6
b0 S
b1000 +
b1000 9
b1000 F
b0 ,
b0 8
b0 E
b0 *
b0 :
b0 G
b10 1
b10 4
b10 R
b10 ]
b100011 .
b100011 7
b100000000010000000100011 (
b100000000010000000100011 /
b100000000010000000100011 b
b10000 !
b10000 %
b10000 )
b10000 3
b10000 P
b10000 \
b10000 a
b100 $
1"
#2700
b101 V
b101 `
0"
#3000
b0 W
b0 ^
b0 @
b0 O
b0 Q
b0 =
b0 I
b0 T
b0 X
b0 _
0Y
1;
b101 <
b101 H
b101 [
b10 D
b10 U
b0 C
b0 N
b0 +
b0 9
b0 F
b1001 *
b1001 :
b1001 G
b11 .
b11 7
b0 2
b0 6
b0 S
b10010010000011 (
b10010010000011 /
b10010010000011 b
b10100 !
b10100 %
b10100 )
b10100 3
b10100 P
b10100 \
b10100 a
b101 $
1"
#3300
0"
#3600
bx V
bx `
b101 X
b101 _
b100 W
b100 ^
b100 @
b100 O
b100 Q
b101 =
b101 I
b101 T
0;
b0 <
b0 H
b0 [
1Y
b11 D
b11 U
b100 C
b100 N
b1001 +
b1001 9
b1001 F
b100 *
b100 :
b100 G
b100011 .
b100011 7
b100 2
b100 6
b100 S
b100100000010001000100011 (
b100100000010001000100011 /
b100100000010001000100011 b
b11000 !
b11000 %
b11000 )
b11000 3
b11000 P
b11000 \
b11000 a
b110 $
1"
#3900
b101 V
b101 `
0"
#4200
b100 W
b100 ^
b100 @
b100 O
b100 Q
b0 =
b0 I
b0 T
b0 X
b0 _
0Y
1;
b101 <
b101 H
b101 [
b10 D
b10 U
b100 C
b100 N
b100 +
b100 9
b100 F
b1010 *
b1010 :
b1010 G
b11 .
b11 7
b100 2
b100 6
b100 S
b10000000010010100000011 (
b10000000010010100000011 /
b10000000010010100000011 b
b11100 !
b11100 %
b11100 )
b11100 3
b11100 P
b11100 \
b11100 a
b111 $
1"
#4500
0"
#4800
b11 @
b11 O
b11 Q
b11 <
b11 H
b11 [
b1 D
b1 U
b11 C
b11 N
b11 +
b11 9
b11 F
b101 *
b101 :
b101 G
b0 1
b0 4
b0 R
b0 ]
b10011 .
b10011 7
b11 2
b11 6
b11 S
b1100000000001010010011 (
b1100000000001010010011 /
b1100000000001010010011 b
b100000 !
b100000 %
b100000 )
b100000 3
b100000 P
b100000 \
b100000 a
b1000 $
1"
#5100
0"
#5400
b110 *
b110 :
b110 G
b1100000000001100010011 (
b1100000000001100010011 /
b1100000000001100010011 b
b100100 !
b100100 %
b100100 )
b100100 3
b100100 P
b100100 \
b100100 a
b1001 $
1"
#5700
0"
#6000
b0 <
b0 H
b0 [
b0 @
b0 O
b0 Q
b0 C
b0 N
b0 +
b0 9
b0 F
b0 *
b0 :
b0 G
b0 2
b0 6
b0 S
b10011 (
b10011 /
b10011 b
b101000 !
b101000 %
b101000 )
b101000 3
b101000 P
b101000 \
b101000 a
b1010 $
1"
#6300
0"
#6600
b111000 '
b111000 -
b111000 ?
b111000 Z
1&
b11 C
b11 N
b11 B
b11 M
b1 @
b1 O
b1 Q
b11 =
b11 I
b11 T
b11 >
b11 J
0;
b100 D
b100 U
b1101 A
b1101 L
b110 +
b110 9
b110 F
b101 ,
b101 8
b101 E
b1100 *
b1100 :
b1100 G
b1100011 .
b1100011 7
b1100 2
b1100 6
b1100 S
b11000101000011001100011 (
b11000101000011001100011 /
b11000101000011001100011 b
b101100 !
b101100 %
b101100 )
b101100 3
b101100 P
b101100 \
b101100 a
b1011 $
1"
#6900
0"
#7200
b0 B
b0 M
b110100 @
b110100 O
b110100 Q
b0 =
b0 I
b0 T
b0 >
b0 J
0&
1;
b110100 <
b110100 H
b110100 [
b1 D
b1 U
b110100 C
b110100 N
b0 A
b0 L
b10100 +
b10100 9
b10100 F
b0 ,
b0 8
b0 E
b1011 *
b1011 :
b1011 G
b1 0
b1 5
b10011 .
b10011 7
b110100 2
b110100 6
b110100 S
b11010000000000010110010011 (
b11010000000000010110010011 /
b11010000000000010110010011 b
b1000100 '
b1000100 -
b1000100 ?
b1000100 Z
b111000 !
b111000 %
b111000 )
b111000 3
b111000 P
b111000 \
b111000 a
b1100 $
1"
#7500
0"
#7800
b0 <
b0 H
b0 [
b0 @
b0 O
b0 Q
b0 C
b0 N
b0 +
b0 9
b0 F
b0 *
b0 :
b0 G
b0 0
b0 5
b0 2
b0 6
b0 S
b10011 (
b10011 /
b10011 b
b111100 !
b111100 %
b111100 )
b111100 3
b111100 P
b111100 \
b111100 a
b1101 $
1"
#8100
0"
#8400
b110100 @
b110100 O
b110100 Q
b110100 B
b110100 M
b1000000 <
b1000000 H
b1000000 [
b110100 '
b110100 -
b110100 ?
b110100 Z
1&
b110100 >
b110100 J
b101 D
b101 U
b1011 ,
b1011 8
b1011 E
b1100111 .
b1100111 7
b1011000000001100111 (
b1011000000001100111 /
b1011000000001100111 b
b1000000 !
b1000000 %
b1000000 )
b1000000 3
b1000000 P
b1000000 \
b1000000 a
b1110 $
1"
#8700
0"
#9000
b1001000 '
b1001000 -
b1001000 ?
b1001000 Z
b1001000 @
b1001000 O
b1001000 Q
b0 >
b0 J
b10100 C
b10100 N
b10100 +
b10100 9
b10100 F
b0 ,
b0 8
b0 E
b1101111 .
b1101111 7
b10100 2
b10100 6
b10100 S
b1010000000000000001101111 (
b1010000000000000001101111 /
b1010000000000000001101111 b
b110100 <
b110100 H
b110100 [
b110100 !
b110100 %
b110100 )
b110100 3
b110100 P
b110100 \
b110100 a
b1111 $
1"
#9300
0"
#9600
0&
b1 D
b1 U
b1000100 C
b1000100 N
b1011100 '
b1011100 -
b1011100 ?
b1011100 Z
b100 +
b100 9
b100 F
b1011 *
b1011 :
b1011 G
b10 0
b10 5
b10011 .
b10011 7
b1000100 2
b1000100 6
b1000100 S
b1000100 @
b1000100 O
b1000100 Q
b100010000000000010110010011 (
b100010000000000010110010011 /
b100010000000000010110010011 b
b1000100 <
b1000100 H
b1000100 [
b0 B
b0 M
b1001000 !
b1001000 %
b1001000 )
b1001000 3
b1001000 P
b1001000 \
b1001000 a
b10000 $
1"
#9900
0"
#10200
b1000100 X
b1000100 _
b1000 @
b1000 O
b1000 Q
b1000100 =
b1000100 I
b1000100 T
bx V
bx `
0;
b0 <
b0 H
b0 [
1Y
b1000 W
b1000 ^
b11 D
b11 U
b1000 C
b1000 N
b1011 +
b1011 9
b1011 F
b1000 *
b1000 :
b1000 G
b0 0
b0 5
b10 1
b10 4
b10 R
b10 ]
b100011 .
b100011 7
b1000 2
b1000 6
b1000 S
b101100000010010000100011 (
b101100000010010000100011 /
b101100000010010000100011 b
b1001100 !
b1001100 %
b1001100 )
b1001100 3
b1001100 P
b1001100 \
b1001100 a
b10001 $
1"
